MANIFEST.in
setup.py
ext/db.c
ext/db.h
ext/defs.h
ext/dump.c
ext/dump.h
ext/record_pb.c
ext/record_pb.h
ext/ring.c
ext/ring.h
ext/serial.c
ext/serial.h
ext/shared_ring.c
ext/shared_ring.h
ext/trace.c
pytrace/__init__.py
pytrace/__main__.py
pytrace/context_utils.py
pytrace.egg-info/PKG-INFO
pytrace.egg-info/SOURCES.txt
pytrace.egg-info/dependency_links.txt
pytrace.egg-info/entry_points.txt
pytrace.egg-info/requires.txt
pytrace.egg-info/top_level.txt
pytrace/reader/__init__.py
pytrace/reader/__main__.py
pytrace/reader/query.py
pytrace/reader/search.py
pytrace/reader/tables.py
pytrace/reader/trace_walker.py
pytrace/reader/urwid_utils.py