Metadata-Version: 1.1
Name: pytrace
Version: 0.2.3
Summary: pytrace is a fast python tracer. pytrace records function calls, arguments and return values. traces aid debugging, profiling and obviate logging.
Home-page: https://github.com/alonho/pytrace
Author: Alon Horev
Author-email: alonho@gmail.com
License: LGPL
Platform: UNKNOWN
Classifier: Development Status :: 3 - Alpha
Classifier: Intended Audience :: Developers
Classifier: Environment :: Console :: Curses
Classifier: License :: OSI Approved :: GNU Library or Lesser General Public License (LGPL)
Classifier: Operating System :: POSIX :: Linux
Classifier: Operating System :: MacOS :: MacOS X
Classifier: Programming Language :: Python :: 2.7
Classifier: Topic :: Software Development :: Debuggers
